[
   {
      "id": "welc",
      "header": "Witaj na mojej skromnej stronie!",
      "content": "Lorem ipsum dolor sit amet, consectetur adipiscing elit. Integer rhoncus facilisis consectetur. Etiam consectetur feugiat nisi nec suscipit. Nunc vitae tempor risus. Duis vel erat tempor, facilisis velit in, imperdiet quam. Praesent vitae ligula lorem. Suspendisse porta euismod dui a dignissim. Vestibulum finibus blandit sollicitudin. Suspendisse pulvinar imperdiet ex sed lacinia. Praesent felis erat, gravida a nisi quis, tristique pretium nibh. Nullam tortor eros, porta non luctus ornare, porttitor molestie ex. Praesent auctor leo libero, id blandit ligula dignissim ac. Ut congue risus eros. Maecenas vitae ipsum a dolor placerat tincidunt. Phasellus non euismod elit. Pellentesque condimentum est odio, sit amet ornare magna rutrum id. Nullam eget eros at risus fringilla euismod ac ut elit. Praesent ipsum elit, viverra sit amet magna vel, tempor accumsan felis. Fusce velit leo, suscipit eget dui eget, dapibus viverra nisl. Sed quis massa orci. Cras efficitur, diam vel egestas rhoncus, lectus est imperdiet magna, at commodo elit justo ac ligula. Sed maximus euismod tristique. Nulla eget ligula pellentesque, accumsan enim a, vestibulum nunc. In enim augue, porta ac tincidunt in, tempor ac nisl. Etiam nibh nibh, auctor id laoreet eget, commodo eget mauris. Interdum et malesuada fames ac ante ipsum primis in faucibus. Maecenas quis tempor lectus, at molestie lacus. Sed commodo dolor sed purus lacinia, ut condimentum lorem condimentum. Phasellus eget molestie erat. Nam pretium ligula et varius ornare. In id felis nisl. Integer varius urna justo, in egestas nibh blandit eget. Sed volutpat risus turpis, non iaculis massa posuere a. Vestibulum ante ipsum primis in faucibus orci luctus et ultrices posuere cubilia Curae; Nam condimentum quam dictum enim aliquet, a tempus tellus mattis. Mauris feugiat est quis varius tristique. Sed non sapien est. Vivamus congue lobortis ipsum pellentesque facilisis. Donec ac neque sit amet urna sollicitudin tincidunt. Vestibulum sollicitudin, mauris vitae porta dictum, nisi turpis iaculis nibh, a mollis turpis augue vitae odio. Etiam consequat lorem non porttitor venenatis. Suspendisse nec tellus sit amet libero consequat luctus et a felis. Donec sodales, magna efficitur rhoncus eleifend, enim metus dapibus mi, nec tristique turpis orci eget neque. Cras ullamcorper consequat volutpat. Donec aliquam luctus augue vitae accumsan. Morbi tempus massa metus, eu condimentum quam malesuada ut. Aliquam erat volutpat. Cras eu dui interdum, tristique ante eu, suscipit orci. Vestibulum at convallis turpis, tincidunt blandit est."
   },
   {
      "id": "second",
      "header": "Witaj na mojej skromnej stronie!",
      "content": "Lorem ipsum dolor sit amet, consectetur adipiscing elit. Integer rhoncus facilisis consectetur. Etiam consectetur feugiat nisi nec suscipit. Nunc vitae tempor risus. Duis vel erat tempor, facilisis velit in, imperdiet quam. Praesent vitae ligula lorem. Suspendisse porta euismod dui a dignissim. Vestibulum finibus blandit sollicitudin. Suspendisse pulvinar imperdiet ex sed lacinia. Praesent felis erat, gravida a nisi quis, tristique pretium nibh. Nullam tortor eros, porta non luctus ornare, porttitor molestie ex. Praesent auctor leo libero, id blandit ligula dignissim ac. Ut congue risus eros. Maecenas vitae ipsum a dolor placerat tincidunt. Phasellus non euismod elit. Pellentesque condimentum est odio, sit amet ornare magna rutrum id. Nullam eget eros at risus fringilla euismod ac ut elit. Praesent ipsum elit, viverra sit amet magna vel, tempor accumsan felis. Fusce velit leo, suscipit eget dui eget, dapibus viverra nisl. Sed quis massa orci. Cras efficitur, diam vel egestas rhoncus, lectus est imperdiet magna, at commodo elit justo ac ligula. Sed maximus euismod tristique. Nulla eget ligula pellentesque, accumsan enim a, vestibulum nunc. In enim augue, porta ac tincidunt in, tempor ac nisl. Etiam nibh nibh, auctor id laoreet eget, commodo eget mauris. Interdum et malesuada fames ac ante ipsum primis in faucibus. Maecenas quis tempor lectus, at molestie lacus. Sed commodo dolor sed purus lacinia, ut condimentum lorem condimentum. Phasellus eget molestie erat. Nam pretium ligula et varius ornare. In id felis nisl. Integer varius urna justo, in egestas nibh blandit eget. Sed volutpat risus turpis, non iaculis massa posuere a. Vestibulum ante ipsum primis in faucibus orci luctus et ultrices posuere cubilia Curae; Nam condimentum quam dictum enim aliquet, a tempus tellus mattis. Mauris feugiat est quis varius tristique. Sed non sapien est. Vivamus congue lobortis ipsum pellentesque facilisis. Donec ac neque sit amet urna sollicitudin tincidunt. Vestibulum sollicitudin, mauris vitae porta dictum, nisi turpis iaculis nibh, a mollis turpis augue vitae odio. Etiam consequat lorem non porttitor venenatis. Suspendisse nec tellus sit amet libero consequat luctus et a felis. Donec sodales, magna efficitur rhoncus eleifend, enim metus dapibus mi, nec tristique turpis orci eget neque. Cras ullamcorper consequat volutpat. Donec aliquam luctus augue vitae accumsan. Morbi tempus massa metus, eu condimentum quam malesuada ut. Aliquam erat volutpat. Cras eu dui interdum, tristique ante eu, suscipit orci. Vestibulum at convallis turpis, tincidunt blandit est."
   }
]